calendar_widget/__init__.py
calendar_widget/calendar_widget.py
calendar_widget-1.0.11.dist-info/METADATA
calendar_widget-1.0.11.dist-info/WHEEL
calendar_widget-1.0.11.dist-info/licenses/LICENSE.md
calendar_widget-1.0.11.dist-info/RECORD
