Metadata-Version: 2.3
Name: calendar_widget
Version: 1.0.11
Summary: Calendar widget for use with python tkinter
Project-URL: Homepage, https://github.com/Spartanlasergun/calendar_widget
Project-URL: Bug Tracker, https://github.com/Spartanlasergun/calendar_widget/issues
Author-email: Spartanlasergun <bns360@live.com>
License-File: LICENSE.md
Classifier: License :: OSI Approved :: GNU Lesser General Public License v2 or later (LGPLv2+)
Classifier: Operating System :: Microsoft :: Windows
Classifier: Programming Language :: Python :: 3
Requires-Python: >=3.8
